classifier/__init__.py
classifier/accuracy.py
classifier/classify.py
classifier/cli.py
classifier/dataprep.py
classifier/models.py
classifier/predict.py
classifier/samples.py
classifier/settings.py
classifier/timeseries.py
classifier/train.py
classifier/utils/__init__.py
classifier/utils/config.py
classifier/utils/general.py
classifier/utils/raster.py
classifier/utils/vector.py
tests/__init__.py
tests/accuracy_test.py
tests/config_test.py
tests/conftest.py
tests/samples_test.py
tests/integration/__init__.py
tests/integration/integration_different_configs_test.py
tests/integration/integration_supervised_singleraster_test.py
tests/integration/integration_supervised_timeseries_test.py
tests/integration/integration_unsupervised_test.py
tests/utils/__init__.py
tests/utils/raster_test.py
tests/utils/vector_test.py
s11_classifier-3.9.0.dist-info/METADATA
s11_classifier-3.9.0.dist-info/WHEEL
s11_classifier-3.9.0.dist-info/top_level.txt
s11_classifier-3.9.0.dist-info/RECORD
